quantflow/__init__.py
quantflow/cli/__init__.py
quantflow/cli/app.py
quantflow/cli/commands/__init__.py
quantflow/cli/commands/base.py
quantflow/cli/commands/crypto.py
quantflow/cli/commands/fred.py
quantflow/cli/commands/stocks.py
quantflow/cli/commands/vault.py
quantflow/cli/script.py
quantflow/cli/settings.py
quantflow/data/__init__.py
quantflow/data/deribit.py
quantflow/data/fed.py
quantflow/data/fiscal_data.py
quantflow/data/fmp.py
quantflow/data/fred.py
quantflow/data/vault.py
quantflow/options/__init__.py
quantflow/options/bs.py
quantflow/options/calibration.py
quantflow/options/inputs.py
quantflow/options/pricer.py
quantflow/options/surface.py
quantflow/py.typed
quantflow/sp/__init__.py
quantflow/sp/base.py
quantflow/sp/bns.py
quantflow/sp/cir.py
quantflow/sp/copula.py
quantflow/sp/dsp.py
quantflow/sp/heston.py
quantflow/sp/jump_diffusion.py
quantflow/sp/ou.py
quantflow/sp/poisson.py
quantflow/sp/weiner.py
quantflow/ta/__init__.py
quantflow/ta/base.py
quantflow/ta/ohlc.py
quantflow/ta/paths.py
quantflow/utils/__init__.py
quantflow/utils/bins.py
quantflow/utils/dates.py
quantflow/utils/distributions.py
quantflow/utils/functions.py
quantflow/utils/interest_rates.py
quantflow/utils/marginal.py
quantflow/utils/numbers.py
quantflow/utils/plot.py
quantflow/utils/transforms.py
quantflow/utils/types.py
quantflow-0.4.2.dist-info/LICENSE
quantflow-0.4.2.dist-info/METADATA
quantflow-0.4.2.dist-info/WHEEL
quantflow-0.4.2.dist-info/entry_points.txt
quantflow-0.4.2.dist-info/RECORD
