Metadata-Version: 2.3
Name: quantflow
Version: 0.4.2
Summary: quantitative analysis
License: BSD-3-Clause
Author: Luca Sbardella
Author-email: luca@quantmind.com
Requires-Python: >=3.11,<4.0
Classifier: License :: OSI Approved :: BSD License
Classifier: Programming Language :: Python :: 3
Classifier: Programming Language :: Python :: 3.11
Classifier: Programming Language :: Python :: 3.12
Classifier: Programming Language :: Python :: 3.13
Provides-Extra: cli
Provides-Extra: data
Requires-Dist: aio-fluid[http] (>=1.2.1) ; extra == "data"
Requires-Dist: asciichartpy (>=1.5.25) ; extra == "cli"
Requires-Dist: async-cache (>=1.1.1) ; extra == "cli"
Requires-Dist: ccy (>=1.7.1)
Requires-Dist: click (>=8.1.7) ; extra == "cli"
Requires-Dist: holidays (>=0.63) ; extra == "cli"
Requires-Dist: polars[pandas,pyarrow] (>=1.11.0)
Requires-Dist: prompt-toolkit (>=3.0.43) ; extra == "cli"
Requires-Dist: pydantic (>=2.0.2)
Requires-Dist: python-dotenv (>=1.0.1)
Requires-Dist: rich (>=13.9.4) ; extra == "cli"
Requires-Dist: scipy (>=1.14.1)
Project-URL: Documentation, https://quantmind.github.io/quantflow/
Project-URL: Homepage, https://github.com/quantmind/quantflow
Project-URL: Repository, https://github.com/quantmind/quantflow
